{
  "id": "ETHUSDT_e5ebae16",
  "symbol": "ETHUSDT",
  "created_at": "2025-12-24T11:39:02.159568",
  "training": {
    "interval": "4h",
    "start_date": "2024-12-24",
    "end_date": "2025-12-24",
    "generations": 100,
    "population_size": 100,
    "rules_per_individual": 8
  },
  "individual": {
    "rules": [
      {
        "indicator": {
          "type": "MACD",
          "params": {
            "fast": 16,
            "slow": 26,
            "signal": 14
          }
        },
        "target": -13.182713669036708,
        "weight": -718802.6260309394
      },
      {
        "indicator": {
          "type": "MACD",
          "params": {
            "fast": 13,
            "slow": 28,
            "signal": 13
          }
        },
        "target": 45.175756694260265,
        "weight": -854960.170241123
      },
      {
        "indicator": {
          "type": "PRICE",
          "params": {
            "period": 1
          }
        },
        "target": 3162.0953988862866,
        "weight": -634011.1543987619
      },
      {
        "indicator": {
          "type": "MACD",
          "params": {
            "fast": 7,
            "slow": 35,
            "signal": 9
          }
        },
        "target": 56.85252162921659,
        "weight": -589973.9567479366
      },
      {
        "indicator": {
          "type": "MACD_HIST",
          "params": {
            "fast": 5,
            "slow": 20,
            "signal": 10
          }
        },
        "target": -22.86242878834579,
        "weight": 146392.64685297708
      },
      {
        "indicator": {
          "type": "MACD",
          "params": {
            "fast": 10,
            "slow": 40,
            "signal": 13
          }
        },
        "target": 5.524697824284558,
        "weight": -941591.2376672855
      },
      {
        "indicator": {
          "type": "MACD_HIST",
          "params": {
            "fast": 9,
            "slow": 35,
            "signal": 15
          }
        },
        "target": 42.50142509984447,
        "weight": -483600.4779191708
      },
      {
        "indicator": {
          "type": "RSI",
          "params": {
            "period": 9
          }
        },
        "target": 31.791040243392025,
        "weight": 889735.2174107912
      }
    ],
    "fitness": 1.6976161472063325
  }
}